tiletanic/__init__.py
tiletanic/base.py
tiletanic/cli.py
tiletanic/tilecover.py
tiletanic/tileschemes.py
tiletanic-1.1.0.dist-info/LICENSE.txt
tiletanic-1.1.0.dist-info/METADATA
tiletanic-1.1.0.dist-info/WHEEL
tiletanic-1.1.0.dist-info/entry_points.txt
tiletanic-1.1.0.dist-info/top_level.txt
tiletanic-1.1.0.dist-info/RECORD
