Metadata-Version: 2.1
Name: tiletanic
Version: 1.1.0
Summary: Geospatial tiling utilities
Home-page: https://github.com/digitalglobe/tiletanic
Author: Patrick Young
Author-email: patrick.young@digitalglobe.com
License: MIT
Platform: UNKNOWN
Classifier: Programming Language :: Python :: 3.6
Classifier: Programming Language :: Python :: 3.7
Classifier: Programming Language :: Python :: 3.8
Requires-Dist: click
Requires-Dist: geojson
Requires-Dist: shapely (>=1.6)
